{
  "totRounds": 20000,
  "ResReward": 1,
  "VisReward": 1,
  "ResProb": [0, 0.1, 0.2, 0.3, 0.4, 0.5, 0.6, 0.7, 0.8, 0.9],
  "VisProb": [0, 0.1, 0.2, 0.3, 0.4, 0.5, 0.6, 0.7, 0.8, 0.9],
  "ResProbLeav": 1,
  "VisProbLeav": 1,
  "negativeRew": -1,
  "experiment": false,
  "inbr": 0,
  "outbr": 0,
  "trainingRep": 30,
  "forRat": 0,
  "alphaT": 0.01,
  "printGen": 100,
  "seed": 1,
  "gammaRange": [0, 0.8],
  "tauRange": 1,
  "netaRange": [0, 1],
  "alphaThRange": 0.01,
  "folder": "./Fig4/abundance_"
}
